{"organizations": [], "uuid": "e21340c314b104d8694e9ada0374df8aa624ad3d", "thread": {"site_full": "thehill.com", "main_image": "http://thehill.com/sites/default/files/article_images/obamabarack120114getty_0.jpg", "site_section": "http://thehill.com/rss/syndicator/21684#", "section_title": "TheHill - Video", "url": "http://thehill.com/video/in-the-news/246124-live-obama-addresses-supreme-courts-o-care-decision", "country": "US", "title": "LIVE: Obama addresses Supreme Court's ObamaCare decision", "performance_score": 0, "site": "thehill.com", "participants_count": 1, "title_full": "LIVE: Obama addresses Supreme Court's ObamaCare decision", "spam_score": 0.0, "site_type": "news", "published": "2015-06-25T18:19:00.000+03:00", "replies_count": 0, "uuid": "e21340c314b104d8694e9ada0374df8aa624ad3d"}, "author": "The Hill Staff", "url": "http://thehill.com/video/in-the-news/246124-live-obama-addresses-supreme-courts-o-care-decision", "ord_in_thread": 0, "title": "LIVE: Obama addresses Supreme Court's ObamaCare decision", "locations": [], "entities": {"persons": [], "locations": [], "organizations": []}, "highlightText": "", "language": "english", "persons": [], "text": "Jon Stewart on Charleston shooting... Stewart held back tears while discussing the Charleston shooting. Rick Perry calls Charleston... An aide said the 2016 contender misspoke and meant to say \"incident.\" Obama thinks Confederate flag '... White House spokesman says Obama thinks flag should come down. Carson: 'The heart of the matter... Ben Carson said further gun control is not the best solution to Wednesday’... McConnell calling Dem bluff on... McConnell reasons that Senate Democrats won’t want to kill Obama’s prized...", "external_links": [], "published": "2015-06-25T18:19:00.000+03:00", "crawled": "2015-06-25T18:40:47.000+03:00", "highlightTitle": "", "social": {"gplus": {"shares": 0}, "pinterest": {"shares": 0}, "vk": {"shares": 0}, "linkedin": {"shares": 0}, "facebook": {"likes": 0, "shares": 0, "comments": 0}, "stumbledupon": {"shares": 0}}}