{"organizations": [], "uuid": "52c07f1d710080c3d16e557d7d92d06c21e60ec5", "thread": {"site_full": "mexico.cnn.com", "main_image": "http://cf.c.ooyala.com/s1MnJudzobNzMvrByETEw0ctXXlySqKv/promo267228034", "site_section": "", "section_title": "", "url": "http://mexico.cnn.com/videos/2015/09/22/obama-recibe-al-papa-a-su-llegada-a-eu", "country": "", "title": "Obama recibe al papa, a su llegada a EU", "performance_score": 0, "site": "cnn.com", "participants_count": 0, "title_full": "Obama recibe al papa, a su llegada a EU", "spam_score": 0.0, "site_type": "news", "published": "2015-09-23T07:00:00.000+03:00", "replies_count": 0, "uuid": "52c07f1d710080c3d16e557d7d92d06c21e60ec5"}, "author": "", "url": "http://mexico.cnn.com/videos/2015/09/22/obama-recibe-al-papa-a-su-llegada-a-eu", "ord_in_thread": 0, "title": "Obama recibe al papa, a su llegada a EU", "locations": [], "entities": {"persons": [], "locations": [], "organizations": []}, "highlightText": "", "language": "spanish", "persons": [], "text": "Obama recibe al papa, a su llegada a EU Obama recibe al papa, a su llegada a EU El papa Francisco llegó a Estados Unidos, luego de realizar una visita a Cuba. Fue recibido por el presidente Obama y su familia Actualizado: 22 de septiembre del 2015 - Comparte esta liga: http://cnn.mx/v005U09 { \"comments\": \"\\r\\n\\r\\n\\r\\n\\r\\n\\r\\n\\r\\n \\r\\n\\r\\n\\r\\n \\r\\n\", \"commentCount\": 0, \"next\": \"0\", \"nextTS\": 0, \"hasMore\": false, \"statusCode\": 200, \"errorCode\": 0, \"statusReason\": \"OK\", \"callId\": \"33eb2cf7c9f84b9e8f7c733c9356ed40\", \"time\": \"2015-09-23T04:01:09.672Z\" } Lo más popular ", "external_links": [], "published": "2015-09-23T07:00:00.000+03:00", "crawled": "2015-09-23T07:01:20.707+03:00", "highlightTitle": "", "social": {"gplus": {"shares": 0}, "pinterest": {"shares": 0}, "vk": {"shares": 0}, "linkedin": {"shares": 0}, "facebook": {"likes": 0, "shares": 0, "comments": 0}, "stumbledupon": {"shares": 0}}}