{"organizations": [], "uuid": "5b1464921dd03d77d0d6212abec612bdd5006189", "thread": {"site_full": "www.huffingtonpost.com", "main_image": "http://img.huffingtonpost.com//asset/600_450/55b29e681d00002f00142988.jpeg", "site_section": "", "section_title": "", "url": "http://www.huffingtonpost.com/entry/obama-half-sister_55b29e40e4b0a13f9d1897f1", "country": "", "title": "Obama Reunites With Half-Sister In Kenya", "performance_score": 1, "site": "huffingtonpost.com", "participants_count": 0, "title_full": "Obama Reunites With Half-Sister In Kenya", "spam_score": 0.0, "site_type": "news", "published": "2015-07-25T02:26:00.000+03:00", "replies_count": 0, "uuid": "5b1464921dd03d77d0d6212abec612bdd5006189"}, "author": "", "url": "http://www.huffingtonpost.com/entry/obama-half-sister_55b29e40e4b0a13f9d1897f1", "ord_in_thread": 0, "title": "Obama Reunites With Half-Sister In Kenya", "locations": ["Nairobi", "Jomo Kenyatta Airport", "Kenya"], "entities": {"persons": [], "locations": [], "organizations": []}, "highlightText": "", "language": "english", "persons": ["Barack Obama", "SAUL LOEB", "Obama", "Auma"], "text": "Obama Reunites With Half-Sister In Kenya Paige Lavender Senior Politics Editor, The Huffington Post Posted: 07/24/2015 | Edited: 2 hours ago President Barack Obama (R) is greeted by his half-sister Auma (2-L) on July 24, 2015 at Nairobi's Jomo Kenyatta Airport after he arrived for the start of his two-day state visit. | SAUL LOEB via Getty Images \nPresident Barack Obama was greeted in Nairobi, Kenya, by his half-sister Auma Obama. \nAuma Obama met the president at Jomo Kenyatta Airport, where he arrived ahead of a two-day visit. Obama was also greeted by Kenyan President Uhuru Kenyatta and other top officials from the country. \nObama dined with other members of his family upon arriving in Kenya, including his step-grandmother and other family members, according to Reuters. \nThis is Obama's first presidential visit to Kenya, where his father was born. President Barack Obama sits alongside his step-grandmother, Mama Sarah (L) and half-sister Auma Obama (R), during a gathering of family at his hotel in Nairobi, Kenya, July 24, 2015. Obama arrived in the Kenyan capital Nairobi late Friday, making his first visit to the country of his father's birth since his election as president. Obama was greeted by Kenyan President Uhuru Kenyatta with a handshake and embrace as he stepped off Air Force One, at the start of a weekend visit during which he will address an entrepreneurship summit and hold talks on trade and investment, counter-terrorism, democracy and human rights. | SAUL LOEB via Getty Images ", "external_links": [], "published": "2015-07-25T02:26:00.000+03:00", "crawled": "2015-07-25T02:26:08.418+03:00", "highlightTitle": "", "social": {"gplus": {"shares": 0}, "pinterest": {"shares": 0}, "vk": {"shares": 0}, "linkedin": {"shares": 0}, "facebook": {"likes": 0, "shares": 0, "comments": 0}, "stumbledupon": {"shares": 0}}}