{"organizations": ["Facebook Copyright", "Huffington Post", "Inc", "Inc."], "uuid": "7f96a6b2ad43021ece0827f316c066710356c46a", "thread": {"site_full": "www.huffingtonpost.com", "main_image": "http://i.huffpost.com/gen/3146756/images/o-DRONE-facebook.jpg", "site_section": "", "section_title": "", "url": "http://www.huffingtonpost.com/2015/07/04/womens-group-uses-drones-_n_7717774.html", "country": "", "title": "Women's Group Uses Drones To Deliver Abortion Pills", "performance_score": 0, "site": "huffingtonpost.com", "participants_count": 0, "title_full": "Women's Group Uses Drones To Deliver Abortion Pills", "spam_score": 0.0, "site_type": "news", "published": "2015-07-04T03:00:00.000+03:00", "replies_count": 0, "uuid": "7f96a6b2ad43021ece0827f316c066710356c46a"}, "author": "", "url": "http://www.huffingtonpost.com/2015/07/04/womens-group-uses-drones-_n_7717774.html", "ord_in_thread": 0, "title": "Women's Group Uses Drones To Deliver Abortion Pills", "locations": ["France"], "entities": {"persons": [], "locations": [], "organizations": []}, "highlightText": "", "language": "english", "persons": ["Sami Sarkis"], "text": "Women's Group Uses Drones To Deliver Abortion Pills HuffPost Live Updated: 07/04/2015 9:59 am EDT Digital camera (dslr) on a flying Unmanned Aerial Vehicle (UAV or Drone), with six rotors, used here for aerial photography or filming, France | Sami Sarkis via Getty Images Click here to view Conversations Conversations Please check the checkbox to indicate your consent Options Get top stories and blog posts emailed to me each day.. Facebook Copyright ©2015 TheHuffingtonPost.com, Inc. \"The Huffington Post\" is a registered trademark of TheHuffingtonPost.com, Inc. All rights reserved. Use this form to alert a HuffPost editor about a factual or typographical error in this story. Notify message * What kind of error is this? * What is the correction? 0 count Describe the error here (1,000 character limit) * Type the words below so we know you are not a cyborg Sign me up for The Morning Email Thanks for your report! ", "external_links": [], "published": "2015-07-04T03:00:00.000+03:00", "crawled": "2015-07-05T22:06:26.000+03:00", "highlightTitle": "", "social": {"gplus": {"shares": 0}, "pinterest": {"shares": 0}, "vk": {"shares": 0}, "linkedin": {"shares": 0}, "facebook": {"likes": 0, "shares": 0, "comments": 0}, "stumbledupon": {"shares": 0}}}